graphs_benicioayala/__init__.py
graphs_benicioayala/heapq.py
graphs_benicioayala/sp.py
graphs_benicioayala-0.0.1.dist-info/METADATA
graphs_benicioayala-0.0.1.dist-info/WHEEL
graphs_benicioayala-0.0.1.dist-info/RECORD
